ard_classifier/__init__.py
ard_classifier/classifier.py
ard_classifier-0.2.0.dist-info/METADATA
ard_classifier-0.2.0.dist-info/WHEEL
ard_classifier-0.2.0.dist-info/licenses/LICENSE
ard_classifier-0.2.0.dist-info/RECORD
